syvio/__init__.py
syvio/main.py
syvio/tools/__init__.py
syvio/tools/sched.bt
syvio/tools/sched.py
syvio/tools/upload.py
syvio/util/__init__.py
syvio/util/bpftrace.py
syvio/util/cli.py
syvio/util/perfetto.py
syvio/util/trace_runner.py
syvio/util/upload.py
syvio-0.0.2.dist-info/METADATA
syvio-0.0.2.dist-info/WHEEL
syvio-0.0.2.dist-info/entry_points.txt
syvio-0.0.2.dist-info/RECORD
